{
  "key": 4,
  "updateAuthority": "FGr9rJSQFP4ypFbJMhCotZh94ciMvcU3dApuDeXRi6vb",
  "mint": "CwWR9JFKuxDCdRHyyijQsFmftCVEsx9DMrBF2463NvbG",
  "data": {
    "name": "Mushroom Farmer",
    "symbol": "KAIJU",
    "uri": "https://assets.kaijucards.io/json/mf-131.json",
    "sellerFeeBasisPoints": 500,
    "creators": [
      {
        "address": "FGr9rJSQFP4ypFbJMhCotZh94ciMvcU3dApuDeXRi6vb",
        "verified": 1,
        "share": 100
      }
    ]
  },
  "primarySaleHappened": 0,
  "isMutable": 1
}