{
  "name": "Wave #335",
  "symbol": "WAV",
  "description": "Waves, a generative artwork collection by Playground, is inspired by the fluidity of the crypto markets",
  "seller_fee_basis_points": 1000,
  "image": "https://www.arweave.net/A3NEKI3nzFDGqZvyHhJV9GyHmA9I20wTE7edbnaB1uQ?ext=png",
  "primary_sale_happened": false,
  "attributes": {
    "hash_id": 23743390428171860,
    "Number_of_colors": 4,
    "width": 12,
    "stroke_thickness": 8,
    "speed": 1.0579,
    "jitter": 0.003915,
    "hue": 69,
    "saturation": 82,
    "brightness": 80,
    "alpha": 30
  },
  "collection": {
    "name": "Waves Collection",
    "family": "Playground on Solana"
  },
  "properties": {
    "files": [
      {
        "uri": "https://www.arweave.net/A3NEKI3nzFDGqZvyHhJV9GyHmA9I20wTE7edbnaB1uQ?ext=png",
        "type": "image/png"
      }
    ],
    "creators": [
      {
        "address": "3nvBhKcMqpg26nhtw76ZioZ21PbhtKQZwu3YsGUoHkki",
        "share": 90
      },
      {
        "address": "D1DahDfPyAdRtELhCX9DZWbi1PyNw57xbsaEg3C5HtSD",
        "share": 10
      }
    ],
    "update_authority": "3nvBhKcMqpg26nhtw76ZioZ21PbhtKQZwu3YsGUoHkki"
  }
}