{
  "name": "Wave #27",
  "symbol": "WAV",
  "description": "Waves, a generative artwork collection by Playground, is inspired by the fluidity of the crypto markets",
  "seller_fee_basis_points": 1000,
  "image": "https://www.arweave.net/i8jnXqW7pr06enPpsHM8HPP2RgYTF3egv8G6qQ6tXGs?ext=png",
  "primary_sale_happened": false,
  "attributes": {
    "hash_id": 1777976933739074,
    "Number_of_colors": 1,
    "width": 26,
    "stroke_thickness": 5,
    "speed": 1.0116999999999998,
    "jitter": 0.0022030999999999995,
    "hue": 317,
    "saturation": 91,
    "brightness": 95,
    "alpha": 25
  },
  "collection": {
    "name": "Waves Collection",
    "family": "Playground on Solana"
  },
  "properties": {
    "files": [
      {
        "uri": "https://www.arweave.net/i8jnXqW7pr06enPpsHM8HPP2RgYTF3egv8G6qQ6tXGs?ext=png",
        "type": "image/png"
      }
    ],
    "creators": [
      {
        "address": "3nvBhKcMqpg26nhtw76ZioZ21PbhtKQZwu3YsGUoHkki",
        "share": 90
      },
      {
        "address": "D1DahDfPyAdRtELhCX9DZWbi1PyNw57xbsaEg3C5HtSD",
        "share": 10
      }
    ],
    "update_authority": "3nvBhKcMqpg26nhtw76ZioZ21PbhtKQZwu3YsGUoHkki"
  }
}