[
  {
    "traitName": "Attributes Count",
    "traitValue": "9",
    "frequency": 1,
    "pct": 0.009000090000900008,
    "desc": "1 of 11111 (0.01%)",
    "example": "https://www.arweave.net/Lcwg8o9uJBGbAJyw9lSUugD1CboWUvvtiKLtePsTEs4?ext=png"
  },
  {
    "traitName": "Pluto",
    "traitValue": "Pluto",
    "frequency": 1,
    "pct": 0.009000090000900008,
    "desc": "1 of 11111 (0.01%)",
    "example": "https://www.arweave.net/f6Bkzkik_fB_fg4q5C-HXjaQ173iBiiVvgEH3FinjK0?ext=png"
  },
  {
    "traitName": "Attributes Count",
    "traitValue": "1",
    "frequency": 1,
    "pct": 0.009000090000900008,
    "desc": "1 of 11111 (0.01%)",
    "example": "https://www.arweave.net/f6Bkzkik_fB_fg4q5C-HXjaQ173iBiiVvgEH3FinjK0?ext=png"
  },
  {
    "traitName": "Hat",
    "traitValue": "Medusa Rainbow",
    "frequency": 13,
    "pct": 0.11700117001170011,
    "desc": "13 of 11111 (0.12%)",
    "example": "https://www.arweave.net/bsR0ydDh470E0tHYdaaqE-9DIgA_6wWDpNptKP9TVng?ext=png"
  },
  {
    "traitName": "Hat",
    "traitValue": "Halo",
    "frequency": 13,
    "pct": 0.11700117001170011,
    "desc": "13 of 11111 (0.12%)",
    "example": "https://www.arweave.net/QenF8WAPN5tzXGvITtH1n22RDCRhN1C-J2xYa8sYLAU?ext=png"
  },
  {
    "traitName": "Hat",
    "traitValue": "Gold Girl",
    "frequency": 19,
    "pct": 0.17100171001710018,
    "desc": "19 of 11111 (0.17%)",
    "example": "https://www.arweave.net/WNa1xOQttPjNrgiVEGr-BqKjGk7afb2Ug-izrqL0hto?ext=png"
  },
  {
    "traitName": "Clothe",
    "traitValue": "Red Studded",
    "frequency": 25,
    "pct": 0.22500225002250024,
    "desc": "25 of 11111 (0.23%)",
    "example": "https://www.arweave.net/Jio_1xlQTcYyruTiqPzuOAosgxbLs4dZsFif0BJ1UFU?ext=png"
  },
  {
    "traitName": "Clothe",
    "traitValue": "Iced Jacket",
    "frequency": 31,
    "pct": 0.2790027900279003,
    "desc": "31 of 11111 (0.28%)",
    "example": "https://www.arweave.net/yeT3htwGy2CESnaNWpnzwkf5WeHrKNn7KNPWMBOHcr8?ext=png"
  },
  {
    "traitName": "Clothe",
    "traitValue": "Spiked Rocker",
    "frequency": 31,
    "pct": 0.2790027900279003,
    "desc": "31 of 11111 (0.28%)",
    "example": "https://www.arweave.net/07L2xd3SZgvHGn9I6rBNc6tCa1g2AxgNEiZfq8mZcss?ext=png"
  },
  {
    "traitName": "Hat",
    "traitValue": "Ice Crown",
    "frequency": 34,
    "pct": 0.3060030600306003,
    "desc": "34 of 11111 (0.31%)",
    "example": "https://www.arweave.net/xg-7pmwkMAOYLYLYNTWJszLgj7aHrpxwodSbkP-eAWk?ext=png"
  },
  {
    "traitName": "Clothe",
    "traitValue": "Gold Pimp",
    "frequency": 43,
    "pct": 0.38700387003870035,
    "desc": "43 of 11111 (0.39%)",
    "example": "https://www.arweave.net/BiR1wm_X-9ZuGv9SVI7XTlrmxp4tdzkLFgMCGpBFGA4?ext=png"
  },
  {
    "traitName": "Eyes",
    "traitValue": "Trippy",
    "frequency": 46,
    "pct": 0.41400414004140035,
    "desc": "46 of 11111 (0.41%)",
    "example": "https://www.arweave.net/ST8Ba1pUvYzYn-38vxcCZ-f8H9txoaED4sOBQn6nb5o?ext=png"
  },
  {
    "traitName": "Mouth",
    "traitValue": "Slimey Tongue",
    "frequency": 49,
    "pct": 0.44100441004410046,
    "desc": "49 of 11111 (0.44%)",
    "example": "https://www.arweave.net/a_ReTHqipK1XKye8rHejoUsyWl5pR73A3HQWPq7unms?ext=png"
  },
  {
    "traitName": "Eyes",
    "traitValue": "Outer Space",
    "frequency": 50,
    "pct": 0.4500045000450005,
    "desc": "50 of 11111 (0.45%)",
    "example": "https://www.arweave.net/GuRjstTT5pDwruJhrx7iQSA4bJfCwct1eE2PFC9H6TE?ext=png"
  },
  {
    "traitName": "Mouth",
    "traitValue": "Gold Kazoo",
    "frequency": 51,
    "pct": 0.45900459004590044,
    "desc": "51 of 11111 (0.46%)",
    "example": "https://www.arweave.net/T4hoRuP9sKB7JPXwjREawnR8VM_7poHiOB_F53IE9x0?ext=png"
  },
  {
    "traitName": "Eyes",
    "traitValue": "Green Galaxy",
    "frequency": 63,
    "pct": 0.5670056700567006,
    "desc": "63 of 11111 (0.57%)",
    "example": "https://www.arweave.net/rweTTyc2mgrxsfe_qmyM9sR8fl8bDvoNb2kFZ0b8O98?ext=png"
  },
  {
    "traitName": "Clothe",
    "traitValue": "Angel Wings",
    "frequency": 94,
    "pct": 0.8460084600846008,
    "desc": "94 of 11111 (0.85%)",
    "example": "https://www.arweave.net/Su9lqHjklnSkdIExOIn-Dn5mh8jNmboYzuQOVeclMps?ext=png"
  },
  {
    "traitName": "Astronaut",
    "traitValue": "Astronaut Hot Box",
    "frequency": 94,
    "pct": 0.8460084600846008,
    "desc": "94 of 11111 (0.85%)",
    "example": "https://www.arweave.net/xg-7pmwkMAOYLYLYNTWJszLgj7aHrpxwodSbkP-eAWk?ext=png"
  },
  {
    "traitName": "Eyes",
    "traitValue": "Blue Laser",
    "frequency": 95,
    "pct": 0.8550085500855009,
    "desc": "95 of 11111 (0.86%)",
    "example": "https://www.arweave.net/udJ0OflqiMJDJV7KB37Xaitm9NYbj3cLlmPZFSnGN1A?ext=png"
  },
  {
    "traitName": "Astronaut",
    "traitValue": "Astronaut",
    "frequency": 96,
    "pct": 0.8640086400864009,
    "desc": "96 of 11111 (0.86%)",
    "example": "https://www.arweave.net/a_ReTHqipK1XKye8rHejoUsyWl5pR73A3HQWPq7unms?ext=png"
  },
  {
    "traitName": "Clothe",
    "traitValue": "UZI Chains",
    "frequency": 96,
    "pct": 0.8640086400864009,
    "desc": "96 of 11111 (0.86%)",
    "example": "https://www.arweave.net/JirPDQyz-w0CfM3px0yxWkF8ovarTgxKAkdIGtW8T0I?ext=png"
  },
  {
    "traitName": "Eyes",
    "traitValue": "Ice Cyclopse",
    "frequency": 99,
    "pct": 0.8910089100891009,
    "desc": "99 of 11111 (0.89%)",
    "example": "https://www.arweave.net/tAkhHwR4uRqDDbrvITJAlxC-dHyMxBK8vFfHSXh4ONc?ext=png"
  },
  {
    "traitName": "Clothe",
    "traitValue": "Pimp",
    "frequency": 101,
    "pct": 0.9090090900909009,
    "desc": "101 of 11111 (0.91%)",
    "example": "https://www.arweave.net/9lIuhHKKAMT72Uz_29pFVqMA-F1ICqRWkKkSc_f9pis?ext=png"
  },
  {
    "traitName": "Clothe",
    "traitValue": "Nahmias Jacket",
    "frequency": 102,
    "pct": 0.9180091800918009,
    "desc": "102 of 11111 (0.92%)",
    "example": "https://www.arweave.net/7vYxR9PvzDm4Vl7oaqIkb50iFKTzBmwSGw8Wqf0vBy4?ext=png"
  },
  {
    "traitName": "Jewelry",
    "traitValue": "All Gold Bling",
    "frequency": 103,
    "pct": 0.927009270092701,
    "desc": "103 of 11111 (0.93%)",
    "example": "https://www.arweave.net/dhdcPzA7LJH6CAzCURDr9n3-hUw30xDo0sxMMeJ_kE4?ext=png"
  },
  {
    "traitName": "Mouth",
    "traitValue": "Cigar",
    "frequency": 103,
    "pct": 0.927009270092701,
    "desc": "103 of 11111 (0.93%)",
    "example": "https://www.arweave.net/viB79O7OaW_24xIJ6ClnwjamshHEiT4BVhOVdIDJlWQ?ext=png"
  },
  {
    "traitName": "Clothe",
    "traitValue": "Wolverine",
    "frequency": 103,
    "pct": 0.927009270092701,
    "desc": "103 of 11111 (0.93%)",
    "example": "https://www.arweave.net/T0WzMkZTfiVYO9vwC4Bu7F2PtZcQdU37dvSsVoQeWfk?ext=png"
  },
  {
    "traitName": "Body",
    "traitValue": "Psychadelic",
    "frequency": 104,
    "pct": 0.9360093600936009,
    "desc": "104 of 11111 (0.94%)",
    "example": "https://www.arweave.net/ngUdbwO48OGimgepl4B_F2NDnJFo0VO-LZ70gUV9xvs?ext=png"
  },
  {
    "traitName": "Hat",
    "traitValue": "Blue Crown",
    "frequency": 104,
    "pct": 0.9360093600936009,
    "desc": "104 of 11111 (0.94%)",
    "example": "https://www.arweave.net/HcHsVILHOBZJzbHTnvkOi_zq9L8zzUmGMEMozHXcOy8?ext=png"
  },
  {
    "traitName": "Mouth",
    "traitValue": "Rainbow Sewn",
    "frequency": 108,
    "pct": 0.972009720097201,
    "desc": "108 of 11111 (0.97%)",
    "example": "https://www.arweave.net/HWhF-BCbQ04lKNtpdu1Lu_YS8zpvQ6iCHfZS2mgDg4M?ext=png"
  },
  {
    "traitName": "Eyes",
    "traitValue": "Green Laser",
    "frequency": 109,
    "pct": 0.981009810098101,
    "desc": "109 of 11111 (0.98%)",
    "example": "https://www.arweave.net/tyISIXgt-emZpDRILD5xpSl4n1WMfsTIMVfXpNo0P88?ext=png"
  },
  {
    "traitName": "Eyes",
    "traitValue": "Red Cyclopse",
    "frequency": 109,
    "pct": 0.981009810098101,
    "desc": "109 of 11111 (0.98%)",
    "example": "https://www.arweave.net/7mW_F_2b-92TpfhWDlzXSwx8lCA4TaQdprsz5SkS_TI?ext=png"
  },
  {
    "traitName": "Body",
    "traitValue": "Trippy",
    "frequency": 109,
    "pct": 0.981009810098101,
    "desc": "109 of 11111 (0.98%)",
    "example": "https://www.arweave.net/RP6FaAUg9xGRstjfn1xR86n248zUtNWlnOL_ZZRLtg4?ext=png"
  },
  {
    "traitName": "Hat",
    "traitValue": "Purple Crown",
    "frequency": 113,
    "pct": 1.0170101701017011,
    "desc": "113 of 11111 (1.02%)",
    "example": "https://www.arweave.net/7NfkznOS_Nd4Zab-ynCrmS3FljDMF2S8C8ATyM_bVU4?ext=png"
  },
  {
    "traitName": "Jewelry",
    "traitValue": "Diamond Earring",
    "frequency": 113,
    "pct": 1.0170101701017011,
    "desc": "113 of 11111 (1.02%)",
    "example": "https://www.arweave.net/7mW_F_2b-92TpfhWDlzXSwx8lCA4TaQdprsz5SkS_TI?ext=png"
  },
  {
    "traitName": "Hat",
    "traitValue": "Medusa",
    "frequency": 114,
    "pct": 1.026010260102601,
    "desc": "114 of 11111 (1.03%)",
    "example": "https://www.arweave.net/vFNL8jh6dkKRD1a1f5EJIf1TfTrEEcY3WN-oqih_tzU?ext=png"
  },
  {
    "traitName": "Mouth",
    "traitValue": "Gold Snarl",
    "frequency": 115,
    "pct": 1.035010350103501,
    "desc": "115 of 11111 (1.04%)",
    "example": "https://www.arweave.net/AByOQOft84ODQKyA3zGLCkEXv_qQUZ3mYhwFgD6gTrw?ext=png"
  },
  {
    "traitName": "Astronaut",
    "traitValue": "Gold Astronaut",
    "frequency": 116,
    "pct": 1.044010440104401,
    "desc": "116 of 11111 (1.04%)",
    "example": "https://www.arweave.net/w2L0KP5eCbdKDznuz9UCEwoJ1vGvlfOXiPPwjktoXAk?ext=png"
  },
  {
    "traitName": "Clothe",
    "traitValue": "Toga",
    "frequency": 118,
    "pct": 1.0620106201062012,
    "desc": "118 of 11111 (1.06%)",
    "example": "https://www.arweave.net/cdW-YYKENvT8BDyE-U9VUgHhJ8jvtLxqg7A96qm9ZLY?ext=png"
  },
  {
    "traitName": "Mouth",
    "traitValue": "Gold Grill",
    "frequency": 119,
    "pct": 1.0710107101071011,
    "desc": "119 of 11111 (1.07%)",
    "example": "https://www.arweave.net/HfjqNWyncBZWLzOe1EJM7IUtQqYBY39_OjJg9MdWcA4?ext=png"
  },
  {
    "traitName": "Clothe",
    "traitValue": "Mummy",
    "frequency": 123,
    "pct": 1.107011070110701,
    "desc": "123 of 11111 (1.11%)",
    "example": "https://www.arweave.net/x-SVF88sKGMbCFILd6MG56HSR2iTrunMCiv6u0NRU0Q?ext=png"
  },
  {
    "traitName": "Hat",
    "traitValue": "Classic Crown",
    "frequency": 124,
    "pct": 1.1160111601116012,
    "desc": "124 of 11111 (1.12%)",
    "example": "https://www.arweave.net/NiS7X9V3rwbAPvRn8_zChex8IZZCIdHmUJDTX_cKQyw?ext=png"
  },
  {
    "traitName": "Hat",
    "traitValue": "Pink Crown",
    "frequency": 126,
    "pct": 1.134011340113401,
    "desc": "126 of 11111 (1.13%)",
    "example": "https://www.arweave.net/ZUKw-br1gv1hmNuhrb9E3TYNYru2XkOcMsFYP353Bf4?ext=png"
  },
  {
    "traitName": "Mouth",
    "traitValue": "Bubblegum",
    "frequency": 127,
    "pct": 1.143011430114301,
    "desc": "127 of 11111 (1.14%)",
    "example": "https://www.arweave.net/X16sVSMu6gT_LTCxs-GkLYGeZUC4PZtr8kCFf3mED-g?ext=png"
  },
  {
    "traitName": "Hat",
    "traitValue": "Yellow Crown",
    "frequency": 129,
    "pct": 1.1610116101161012,
    "desc": "129 of 11111 (1.16%)",
    "example": "https://www.arweave.net/JUNaSb5EgAvA4Wxks31sgCVqBiCCq3GjFj5uAAdIcHM?ext=png"
  },
  {
    "traitName": "Mouth",
    "traitValue": "Tobacco Pipe",
    "frequency": 132,
    "pct": 1.188011880118801,
    "desc": "132 of 11111 (1.19%)",
    "example": "https://www.arweave.net/f-yXFaqmvr5ur3Ac8h1Nc4rfElsFiIHXpiAWW2Lziu0?ext=png"
  },
  {
    "traitName": "Eyes",
    "traitValue": "Bandage",
    "frequency": 132,
    "pct": 1.188011880118801,
    "desc": "132 of 11111 (1.19%)",
    "example": "https://www.arweave.net/srdE7L9kv7-fzynBaYLGzK2ttxFWHdQ8JrCZH11qLBw?ext=png"
  },
  {
    "traitName": "Hat",
    "traitValue": "Fiery Medusa",
    "frequency": 132,
    "pct": 1.188011880118801,
    "desc": "132 of 11111 (1.19%)",
    "example": "https://www.arweave.net/5Rdk1zh6jiP6CvLkji7jemB7G3SfCQx-WxOR68jICf4?ext=png"
  },
  {
    "traitName": "Hat",
    "traitValue": "Captain",
    "frequency": 167,
    "pct": 1.5030150301503014,
    "desc": "167 of 11111 (1.50%)",
    "example": "https://www.arweave.net/f-yXFaqmvr5ur3Ac8h1Nc4rfElsFiIHXpiAWW2Lziu0?ext=png"
  },
  {
    "traitName": "Clothe",
    "traitValue": "Pink Tee",
    "frequency": 184,
    "pct": 1.6560165601656014,
    "desc": "184 of 11111 (1.66%)",
    "example": "https://www.arweave.net/NVR_BhDcClJ4fQj7Gj6LvMsF0jUOke0dHyGO843KQF8?ext=png"
  },
  {
    "traitName": "Hat",
    "traitValue": "Bell Boy",
    "frequency": 185,
    "pct": 1.6650166501665016,
    "desc": "185 of 11111 (1.67%)",
    "example": "https://www.arweave.net/8JH10S-bXc_i1eS8jegMGBzsaL7ObWVYU1Zx6wqLJfY?ext=png"
  },
  {
    "traitName": "Clothe",
    "traitValue": "Black Tee",
    "frequency": 192,
    "pct": 1.7280172801728018,
    "desc": "192 of 11111 (1.73%)",
    "example": "https://www.arweave.net/WNa1xOQttPjNrgiVEGr-BqKjGk7afb2Ug-izrqL0hto?ext=png"
  },
  {
    "traitName": "Hat",
    "traitValue": "White",
    "frequency": 193,
    "pct": 1.7370173701737017,
    "desc": "193 of 11111 (1.74%)",
    "example": "https://www.arweave.net/P11xsQ1Y-TfJj4QvyMKbB9m2HETo5f_K3W9A0MeQtj0?ext=png"
  },
  {
    "traitName": "Clothe",
    "traitValue": "Green Turtleneck",
    "frequency": 196,
    "pct": 1.7640176401764018,
    "desc": "196 of 11111 (1.76%)",
    "example": "https://www.arweave.net/oJUMCAtQLD9nTExz_PZQ9cltvvrvOspS-FOY6zUFPro?ext=png"
  },
  {
    "traitName": "Clothe",
    "traitValue": "Blue Tee",
    "frequency": 196,
    "pct": 1.7640176401764018,
    "desc": "196 of 11111 (1.76%)",
    "example": "https://www.arweave.net/NFeIZWruLJlYVIzo4MFSRV1lzo691NCPZ_45T0_vbVw?ext=png"
  },
  {
    "traitName": "Clothe",
    "traitValue": "Red Hawaiin",
    "frequency": 199,
    "pct": 1.791017910179102,
    "desc": "199 of 11111 (1.79%)",
    "example": "https://www.arweave.net/8y0ClrYjzENRhKLwLtYKGBKgVbK3T_aEl_1hgs-AiYs?ext=png"
  },
  {
    "traitName": "Clothe",
    "traitValue": "Black Hoodie",
    "frequency": 206,
    "pct": 1.854018540185402,
    "desc": "206 of 11111 (1.85%)",
    "example": "https://www.arweave.net/Z2aPirpabGCl1FT2MMwPpMmwEVxHwJmNWYuxjuajaBw?ext=png"
  },
  {
    "traitName": "Clothe",
    "traitValue": "White Tee",
    "frequency": 207,
    "pct": 1.8630186301863016,
    "desc": "207 of 11111 (1.86%)",
    "example": "https://www.arweave.net/7NfkznOS_Nd4Zab-ynCrmS3FljDMF2S8C8ATyM_bVU4?ext=png"
  },
  {
    "traitName": "Hat",
    "traitValue": "Sheriff",
    "frequency": 208,
    "pct": 1.8720187201872018,
    "desc": "208 of 11111 (1.87%)",
    "example": "https://www.arweave.net/1bhb9swprI62y-7dyCt8PV9utcDhLrKkr6FPXXxBGcU?ext=png"
  },
  {
    "traitName": "Clothe",
    "traitValue": "Pink Marni and Chains",
    "frequency": 211,
    "pct": 1.899018990189902,
    "desc": "211 of 11111 (1.90%)",
    "example": "https://www.arweave.net/CrRlNzpcWWIN4ERnscfHnJ7RCCBxsSHOY_zfphahF7A?ext=png"
  },
  {
    "traitName": "Clothe",
    "traitValue": "Military Officer",
    "frequency": 212,
    "pct": 1.908019080190802,
    "desc": "212 of 11111 (1.91%)",
    "example": "https://www.arweave.net/06vLgNoZ7dfx9xkPtcmp2vy7RrVQq0wkHP3YndkCtJE?ext=png"
  },
  {
    "traitName": "Hat",
    "traitValue": "AWGE Trucker",
    "frequency": 213,
    "pct": 1.917019170191702,
    "desc": "213 of 11111 (1.92%)",
    "example": "https://www.arweave.net/36vU96lLc79AhRj5hhN7z65m0n6wD1RqDU9p5UqC7aU?ext=png"
  },
  {
    "traitName": "Clothe",
    "traitValue": "Green Hawaiin",
    "frequency": 215,
    "pct": 1.935019350193502,
    "desc": "215 of 11111 (1.94%)",
    "example": "https://www.arweave.net/LdVXOSIxuc_A1oXVqaaQEjTVzEXV8WCYGDq1ETJtpy4?ext=png"
  },
  {
    "traitName": "Clothe",
    "traitValue": "GOAT Jersey",
    "frequency": 215,
    "pct": 1.935019350193502,
    "desc": "215 of 11111 (1.94%)",
    "example": "https://www.arweave.net/WQHB1YzhmYZ_l7CfJMpEMnew2s1pyu2cavTMvxA1PfM?ext=png"
  },
  {
    "traitName": "Hat",
    "traitValue": "Sailor",
    "frequency": 217,
    "pct": 1.9530195301953017,
    "desc": "217 of 11111 (1.95%)",
    "example": "https://www.arweave.net/mLFOBDuQsbVB2xfDuuWG7_VfElZNVWEf1dqC1VjYQL8?ext=png"
  },
  {
    "traitName": "Clothe",
    "traitValue": "Fishing",
    "frequency": 217,
    "pct": 1.9530195301953017,
    "desc": "217 of 11111 (1.95%)",
    "example": "https://www.arweave.net/6NIKz7ICxO7otQexurjWPCmTKxoRMoui9_dwc3MhPaQ?ext=png"
  },
  {
    "traitName": "Jewelry",
    "traitValue": "Red Diamond",
    "frequency": 218,
    "pct": 1.962019620196202,
    "desc": "218 of 11111 (1.96%)",
    "example": "https://www.arweave.net/mLFOBDuQsbVB2xfDuuWG7_VfElZNVWEf1dqC1VjYQL8?ext=png"
  },
  {
    "traitName": "Clothe",
    "traitValue": "BIRD",
    "frequency": 219,
    "pct": 1.971019710197102,
    "desc": "219 of 11111 (1.97%)",
    "example": "https://www.arweave.net/3L0L3MV61vMGycdBlh_yGu2Aqc__g-1NyarcslH0REE?ext=png"
  },
  {
    "traitName": "Jewelry",
    "traitValue": "Purple Diamond",
    "frequency": 220,
    "pct": 1.9800198001980018,
    "desc": "220 of 11111 (1.98%)",
    "example": "https://www.arweave.net/KYPiTtoz18U1gOSSeOAnz4WrPqykkimLFO8_g93nuyo?ext=png"
  },
  {
    "traitName": "Clothe",
    "traitValue": "Purple Hoodie",
    "frequency": 220,
    "pct": 1.9800198001980018,
    "desc": "220 of 11111 (1.98%)",
    "example": "https://www.arweave.net/5gFETgFJUoU1Q6Wf6nA9Ut-MB65IvGthZlwi7LQHQno?ext=png"
  },
  {
    "traitName": "Hair",
    "traitValue": "Two Tone",
    "frequency": 221,
    "pct": 1.989019890198902,
    "desc": "221 of 11111 (1.99%)",
    "example": "https://www.arweave.net/uj6hF7jupckaL2qNdM_AQSSHrJ8lNo9viC0gy5iJiQY?ext=png"
  },
  {
    "traitName": "Clothe",
    "traitValue": "Blue Hawaiin",
    "frequency": 221,
    "pct": 1.989019890198902,
    "desc": "221 of 11111 (1.99%)",
    "example": "https://www.arweave.net/FdN8nX_abZY3sUx_tLKsTphXCCikGBKsrK-aLoK0U40?ext=png"
  },
  {
    "traitName": "Clothe",
    "traitValue": "Life Vest",
    "frequency": 222,
    "pct": 1.998019980199802,
    "desc": "222 of 11111 (2.00%)",
    "example": "https://www.arweave.net/ZfjmlADOQfMZvP2W-DzjbNoHucVdULDy05Ic6SfUpIc?ext=png"
  },
  {
    "traitName": "Clothe",
    "traitValue": "Purple Turtleneck",
    "frequency": 231,
    "pct": 2.079020790207902,
    "desc": "231 of 11111 (2.08%)",
    "example": "https://www.arweave.net/36vU96lLc79AhRj5hhN7z65m0n6wD1RqDU9p5UqC7aU?ext=png"
  },
  {
    "traitName": "Clothe",
    "traitValue": "Blue Turtleneck and Chains",
    "frequency": 232,
    "pct": 2.088020880208802,
    "desc": "232 of 11111 (2.09%)",
    "example": "https://www.arweave.net/QQty2e3G10euUSxzdC_mXy2goKXmI7T15k2gEv1uVe0?ext=png"
  },
  {
    "traitName": "Mouth",
    "traitValue": "Backwood",
    "frequency": 237,
    "pct": 2.133021330213302,
    "desc": "237 of 11111 (2.13%)",
    "example": "https://www.arweave.net/FdN8nX_abZY3sUx_tLKsTphXCCikGBKsrK-aLoK0U40?ext=png"
  },
  {
    "traitName": "Clothe",
    "traitValue": "Beater",
    "frequency": 245,
    "pct": 2.2050220502205025,
    "desc": "245 of 11111 (2.21%)",
    "example": "https://www.arweave.net/f-yXFaqmvr5ur3Ac8h1Nc4rfElsFiIHXpiAWW2Lziu0?ext=png"
  },
  {
    "traitName": "Clothe",
    "traitValue": "Denim",
    "frequency": 251,
    "pct": 2.2590225902259022,
    "desc": "251 of 11111 (2.26%)",
    "example": "https://www.arweave.net/fF6Y2BXn2z1HwawetxcH0WMK1HKPn3XSFa74Dm3gcco?ext=png"
  },
  {
    "traitName": "Clothe",
    "traitValue": "Grey Marni",
    "frequency": 255,
    "pct": 2.2950229502295025,
    "desc": "255 of 11111 (2.30%)",
    "example": "https://www.arweave.net/PHd-qZbzFVK15fd6nd1UToHNt-flZuAm4AbaVYnnfjw?ext=png"
  },
  {
    "traitName": "Mouth",
    "traitValue": "Two Tone Grill",
    "frequency": 285,
    "pct": 2.5650256502565023,
    "desc": "285 of 11111 (2.57%)",
    "example": "https://www.arweave.net/8EeYsuw3scfgpGgA-5tN-NkioWTRg47VSGGe1flwlKo?ext=png"
  },
  {
    "traitName": "Jewelry",
    "traitValue": "Blue Diamond",
    "frequency": 299,
    "pct": 2.6910269102691027,
    "desc": "299 of 11111 (2.69%)",
    "example": "https://www.arweave.net/tyISIXgt-emZpDRILD5xpSl4n1WMfsTIMVfXpNo0P88?ext=png"
  },
  {
    "traitName": "Hat",
    "traitValue": "Green Uzi Whip",
    "frequency": 300,
    "pct": 2.7000270002700026,
    "desc": "300 of 11111 (2.70%)",
    "example": "https://www.arweave.net/tyISIXgt-emZpDRILD5xpSl4n1WMfsTIMVfXpNo0P88?ext=png"
  },
  {
    "traitName": "Hat",
    "traitValue": "Red Beanie",
    "frequency": 301,
    "pct": 2.709027090270903,
    "desc": "301 of 11111 (2.71%)",
    "example": "https://www.arweave.net/HfjqNWyncBZWLzOe1EJM7IUtQqYBY39_OjJg9MdWcA4?ext=png"
  },
  {
    "traitName": "Hat",
    "traitValue": "Black Girl",
    "frequency": 302,
    "pct": 2.7180271802718026,
    "desc": "302 of 11111 (2.72%)",
    "example": "https://www.arweave.net/HWhF-BCbQ04lKNtpdu1Lu_YS8zpvQ6iCHfZS2mgDg4M?ext=png"
  },
  {
    "traitName": "Hat",
    "traitValue": "No Hat",
    "frequency": 305,
    "pct": 2.7450274502745025,
    "desc": "305 of 11111 (2.75%)",
    "example": "https://www.arweave.net/6R8IwbDb4m9wtPuCcz7ZpgfN6aFoedahkltW42WJUHk?ext=png"
  },
  {
    "traitName": "Clothe",
    "traitValue": "Red Turtleneck",
    "frequency": 307,
    "pct": 2.763027630276303,
    "desc": "307 of 11111 (2.76%)",
    "example": "https://www.arweave.net/sRI-sywZgyd5N3y8qERYI3xbWCL3YW5GpS463orIDGQ?ext=png"
  },
  {
    "traitName": "Hat",
    "traitValue": "Leather Bucket",
    "frequency": 308,
    "pct": 2.772027720277203,
    "desc": "308 of 11111 (2.77%)",
    "example": "https://www.arweave.net/QjvybSyO62xvKGSoYVcpMnZZz8SDfGjwWehNXRtc-YQ?ext=png"
  },
  {
    "traitName": "Hat",
    "traitValue": "Starry Yellow Bandana",
    "frequency": 316,
    "pct": 2.844028440284403,
    "desc": "316 of 11111 (2.84%)",
    "example": "https://www.arweave.net/Ar9AQvdmkhgBn9zdGVPgOmKkidJH1vvuS-V1SJ13mdg?ext=png"
  },
  {
    "traitName": "Hat",
    "traitValue": "Jester",
    "frequency": 316,
    "pct": 2.844028440284403,
    "desc": "316 of 11111 (2.84%)",
    "example": "https://www.arweave.net/srdE7L9kv7-fzynBaYLGzK2ttxFWHdQ8JrCZH11qLBw?ext=png"
  },
  {
    "traitName": "Hat",
    "traitValue": "Classic LUV Cap",
    "frequency": 318,
    "pct": 2.862028620286203,
    "desc": "318 of 11111 (2.86%)",
    "example": "https://www.arweave.net/9lIuhHKKAMT72Uz_29pFVqMA-F1ICqRWkKkSc_f9pis?ext=png"
  },
  {
    "traitName": "Hat",
    "traitValue": "Yellow Drew Dad Hat",
    "frequency": 321,
    "pct": 2.8890288902889028,
    "desc": "321 of 11111 (2.89%)",
    "example": "https://www.arweave.net/UageQ3NwCNpe2bNxppIFrHx9Ab9963jCn8SWqVeUs7I?ext=png"
  },
  {
    "traitName": "Hat",
    "traitValue": "Purple Beanie",
    "frequency": 324,
    "pct": 2.9160291602916026,
    "desc": "324 of 11111 (2.92%)",
    "example": "https://www.arweave.net/Z2aPirpabGCl1FT2MMwPpMmwEVxHwJmNWYuxjuajaBw?ext=png"
  },
  {
    "traitName": "Hat",
    "traitValue": "Red LUV Cap",
    "frequency": 326,
    "pct": 2.934029340293403,
    "desc": "326 of 11111 (2.93%)",
    "example": "https://www.arweave.net/2zFfOs60GBxDDt7VQ3sPNu4XXLXw8mDNzd-so1UW7-0?ext=png"
  },
  {
    "traitName": "Hair",
    "traitValue": "Rainbow",
    "frequency": 327,
    "pct": 2.943029430294303,
    "desc": "327 of 11111 (2.94%)",
    "example": "https://www.arweave.net/PHd-qZbzFVK15fd6nd1UToHNt-flZuAm4AbaVYnnfjw?ext=png"
  },
  {
    "traitName": "Hat",
    "traitValue": "Black Perse Trucker",
    "frequency": 328,
    "pct": 2.952029520295203,
    "desc": "328 of 11111 (2.95%)",
    "example": "https://www.arweave.net/8EeYsuw3scfgpGgA-5tN-NkioWTRg47VSGGe1flwlKo?ext=png"
  },
  {
    "traitName": "Hat",
    "traitValue": "Icey Beanie",
    "frequency": 328,
    "pct": 2.952029520295203,
    "desc": "328 of 11111 (2.95%)",
    "example": "https://www.arweave.net/OusoDUMuzsgGE8_ufDXc7ns9p1x7G080rh_qNqM-6Bc?ext=png"
  },
  {
    "traitName": "Jewelry",
    "traitValue": "Gold Diamond",
    "frequency": 329,
    "pct": 2.961029610296103,
    "desc": "329 of 11111 (2.96%)",
    "example": "https://www.arweave.net/vgNSt32VmmzK_AXRN8GhYAzHzRa4YULZngq2PkxGG3k?ext=png"
  },
  {
    "traitName": "Hat",
    "traitValue": "Dad Hat",
    "frequency": 332,
    "pct": 2.988029880298803,
    "desc": "332 of 11111 (2.99%)",
    "example": "https://www.arweave.net/oJUMCAtQLD9nTExz_PZQ9cltvvrvOspS-FOY6zUFPro?ext=png"
  },
  {
    "traitName": "Hat",
    "traitValue": "Starry Blue Bandana",
    "frequency": 333,
    "pct": 2.997029970299703,
    "desc": "333 of 11111 (3.00%)",
    "example": "https://www.arweave.net/NFeIZWruLJlYVIzo4MFSRV1lzo691NCPZ_45T0_vbVw?ext=png"
  },
  {
    "traitName": "Mouth",
    "traitValue": "Gold Tooth",
    "frequency": 333,
    "pct": 2.997029970299703,
    "desc": "333 of 11111 (3.00%)",
    "example": "https://www.arweave.net/8HZvKpj5j4kr0Ph06QiulezX_X3kFFc-Uvqy6rnnku4?ext=png"
  },
  {
    "traitName": "Hat",
    "traitValue": "Drew Dad Hat",
    "frequency": 336,
    "pct": 3.024030240302403,
    "desc": "336 of 11111 (3.02%)",
    "example": "https://www.arweave.net/pioLWnQ14zEyTBwpP9PO69OpIeo3fabzbYpd6E62fqM?ext=png"
  },
  {
    "traitName": "Hat",
    "traitValue": "Purple Uzi Whip",
    "frequency": 336,
    "pct": 3.024030240302403,
    "desc": "336 of 11111 (3.02%)",
    "example": "https://www.arweave.net/wIeW8bIq01P6MULAXnFYDyCi0Db694MCjJcGjEKQ0h0?ext=png"
  },
  {
    "traitName": "Hat",
    "traitValue": "VD Hat",
    "frequency": 345,
    "pct": 3.105031050310503,
    "desc": "345 of 11111 (3.11%)",
    "example": "https://www.arweave.net/tAkhHwR4uRqDDbrvITJAlxC-dHyMxBK8vFfHSXh4ONc?ext=png"
  },
  {
    "traitName": "Hat",
    "traitValue": "MIRACLE",
    "frequency": 348,
    "pct": 3.1320313203132035,
    "desc": "348 of 11111 (3.13%)",
    "example": "https://www.arweave.net/PuKz7zf8k8HwMVSU0mrV9ykH5W1UcsODkkriTLzDd2U?ext=png"
  },
  {
    "traitName": "Hat",
    "traitValue": "Pink LUV Cap",
    "frequency": 348,
    "pct": 3.1320313203132035,
    "desc": "348 of 11111 (3.13%)",
    "example": "https://www.arweave.net/LdVXOSIxuc_A1oXVqaaQEjTVzEXV8WCYGDq1ETJtpy4?ext=png"
  },
  {
    "traitName": "Clothe",
    "traitValue": "Wheres Waldo",
    "frequency": 350,
    "pct": 3.150031500315003,
    "desc": "350 of 11111 (3.15%)",
    "example": "https://www.arweave.net/MGfnQAsQoOlkTlILBiq-q2GsXhhh52mD9TAd2p-mhyc?ext=png"
  },
  {
    "traitName": "Eyes",
    "traitValue": "3D Glasses",
    "frequency": 352,
    "pct": 3.1680316803168034,
    "desc": "352 of 11111 (3.17%)",
    "example": "https://www.arweave.net/Z2aPirpabGCl1FT2MMwPpMmwEVxHwJmNWYuxjuajaBw?ext=png"
  },
  {
    "traitName": "Hat",
    "traitValue": "Pink Trucker",
    "frequency": 357,
    "pct": 3.2130321303213036,
    "desc": "357 of 11111 (3.21%)",
    "example": "https://www.arweave.net/Hm52aXpfvE7tinV_q9U6SBSJxxz0S0SIYqQ1jLPmcgI?ext=png"
  },
  {
    "traitName": "Hat",
    "traitValue": "Yellow Uzi Whip",
    "frequency": 358,
    "pct": 3.222032220322203,
    "desc": "358 of 11111 (3.22%)",
    "example": "https://www.arweave.net/Lyjtp5BkVPGoUJAPwR6-yPKiSmsYDSZ_duVYQAb9j4Q?ext=png"
  },
  {
    "traitName": "Hat",
    "traitValue": "Devil Horns",
    "frequency": 358,
    "pct": 3.222032220322203,
    "desc": "358 of 11111 (3.22%)",
    "example": "https://www.arweave.net/MGfnQAsQoOlkTlILBiq-q2GsXhhh52mD9TAd2p-mhyc?ext=png"
  },
  {
    "traitName": "Hat",
    "traitValue": "Blue Uzi Whip",
    "frequency": 362,
    "pct": 3.258032580325803,
    "desc": "362 of 11111 (3.26%)",
    "example": "https://www.arweave.net/vgNSt32VmmzK_AXRN8GhYAzHzRa4YULZngq2PkxGG3k?ext=png"
  },
  {
    "traitName": "Hat",
    "traitValue": "Spinner",
    "frequency": 365,
    "pct": 3.285032850328503,
    "desc": "365 of 11111 (3.29%)",
    "example": "https://www.arweave.net/K_K9fVooKooh47YRKVBGu48dWCySpQhQtZ1HhvipbAE?ext=png"
  },
  {
    "traitName": "Hat",
    "traitValue": "Spider Bucket",
    "frequency": 366,
    "pct": 3.2940329403294033,
    "desc": "366 of 11111 (3.29%)",
    "example": "https://www.arweave.net/s7tqahpJZ1xLTqnRKvgMAJNXZYLako2yPb6iNNg7Kxs?ext=png"
  },
  {
    "traitName": "Hat",
    "traitValue": "Mohawk",
    "frequency": 369,
    "pct": 3.3210332103321036,
    "desc": "369 of 11111 (3.32%)",
    "example": "https://www.arweave.net/TW2ccD8filIyp0wEo1mG-ruxdX62fgQU8euZjEycSwM?ext=png"
  },
  {
    "traitName": "Clothe",
    "traitValue": "Lake Show",
    "frequency": 404,
    "pct": 3.6360363603636037,
    "desc": "404 of 11111 (3.64%)",
    "example": "https://www.arweave.net/S6FoXphsmQq8GF5n1ULu25hnnTohG9iLfZwaHbv4c-0?ext=png"
  },
  {
    "traitName": "Clothe",
    "traitValue": "Pink Marni",
    "frequency": 412,
    "pct": 3.708037080370804,
    "desc": "412 of 11111 (3.71%)",
    "example": "https://www.arweave.net/aBQjIJrbtZufRDKQk4rG0oGrXcd4NI5166ibIZL2V48?ext=png"
  },
  {
    "traitName": "Clothe",
    "traitValue": "Vs The World Chain",
    "frequency": 416,
    "pct": 3.7440374403744037,
    "desc": "416 of 11111 (3.74%)",
    "example": "https://www.arweave.net/t337Wy99i3xW2nI36pwbpQZxbzSPnp8Ee8wvRv4-RW4?ext=png"
  },
  {
    "traitName": "Clothe",
    "traitValue": "Prison",
    "frequency": 424,
    "pct": 3.816038160381604,
    "desc": "424 of 11111 (3.82%)",
    "example": "https://www.arweave.net/PuKz7zf8k8HwMVSU0mrV9ykH5W1UcsODkkriTLzDd2U?ext=png"
  },
  {
    "traitName": "Clothe",
    "traitValue": "Blue Turtleneck",
    "frequency": 425,
    "pct": 3.825038250382504,
    "desc": "425 of 11111 (3.83%)",
    "example": "https://www.arweave.net/Ar9AQvdmkhgBn9zdGVPgOmKkidJH1vvuS-V1SJ13mdg?ext=png"
  },
  {
    "traitName": "Clothe",
    "traitValue": "Inmate",
    "frequency": 427,
    "pct": 3.8430384303843037,
    "desc": "427 of 11111 (3.84%)",
    "example": "https://www.arweave.net/OLoTIU4e_WG4eqxIQIDUKYgMYr2adeXWl7rpzDEwRtE?ext=png"
  },
  {
    "traitName": "Clothe",
    "traitValue": "Jailhouse",
    "frequency": 429,
    "pct": 3.861038610386104,
    "desc": "429 of 11111 (3.86%)",
    "example": "https://www.arweave.net/cFxXlHJbeXY7rqqXgaV3GWthm1mnOxTSo4yJ0hIktQ8?ext=png"
  },
  {
    "traitName": "Clothe",
    "traitValue": "No Shirt",
    "frequency": 432,
    "pct": 3.888038880388804,
    "desc": "432 of 11111 (3.89%)",
    "example": "https://www.arweave.net/JPf1Pz5BloDAkBa2uAuqjQBuxWN0eme5IunfZpV34Lw?ext=png"
  },
  {
    "traitName": "Clothe",
    "traitValue": "Zen Master",
    "frequency": 447,
    "pct": 4.023040230402304,
    "desc": "447 of 11111 (4.02%)",
    "example": "https://www.arweave.net/pioLWnQ14zEyTBwpP9PO69OpIeo3fabzbYpd6E62fqM?ext=png"
  },
  {
    "traitName": "Clothe",
    "traitValue": "Yellow Marni",
    "frequency": 455,
    "pct": 4.095040950409504,
    "desc": "455 of 11111 (4.10%)",
    "example": "https://www.arweave.net/HWhF-BCbQ04lKNtpdu1Lu_YS8zpvQ6iCHfZS2mgDg4M?ext=png"
  },
  {
    "traitName": "Clothe",
    "traitValue": "LUV Chain",
    "frequency": 464,
    "pct": 4.176041760417604,
    "desc": "464 of 11111 (4.18%)",
    "example": "https://www.arweave.net/HfjqNWyncBZWLzOe1EJM7IUtQqYBY39_OjJg9MdWcA4?ext=png"
  },
  {
    "traitName": "Mouth",
    "traitValue": "Rainbow Grill",
    "frequency": 524,
    "pct": 4.716047160471605,
    "desc": "524 of 11111 (4.72%)",
    "example": "https://www.arweave.net/pioLWnQ14zEyTBwpP9PO69OpIeo3fabzbYpd6E62fqM?ext=png"
  },
  {
    "traitName": "Eyes",
    "traitValue": "OG Cyborg",
    "frequency": 526,
    "pct": 4.7340473404734045,
    "desc": "526 of 11111 (4.73%)",
    "example": "https://www.arweave.net/Ar9AQvdmkhgBn9zdGVPgOmKkidJH1vvuS-V1SJ13mdg?ext=png"
  },
  {
    "traitName": "Eyes",
    "traitValue": "Blue Cyborg",
    "frequency": 527,
    "pct": 4.743047430474305,
    "desc": "527 of 11111 (4.74%)",
    "example": "https://www.arweave.net/6ham-hnY58MH-p_vPSsFcV2byDehXcRxFMwVUsOJ_XU?ext=png"
  },
  {
    "traitName": "Body",
    "traitValue": "Ice",
    "frequency": 529,
    "pct": 4.761047610476105,
    "desc": "529 of 11111 (4.76%)",
    "example": "https://www.arweave.net/oJUMCAtQLD9nTExz_PZQ9cltvvrvOspS-FOY6zUFPro?ext=png"
  },
  {
    "traitName": "Mouth",
    "traitValue": "Purple Sewn",
    "frequency": 532,
    "pct": 4.788047880478804,
    "desc": "532 of 11111 (4.79%)",
    "example": "https://www.arweave.net/9lIuhHKKAMT72Uz_29pFVqMA-F1ICqRWkKkSc_f9pis?ext=png"
  },
  {
    "traitName": "Mouth",
    "traitValue": "Red Sewn",
    "frequency": 533,
    "pct": 4.797047970479705,
    "desc": "533 of 11111 (4.80%)",
    "example": "https://www.arweave.net/NVR_BhDcClJ4fQj7Gj6LvMsF0jUOke0dHyGO843KQF8?ext=png"
  },
  {
    "traitName": "Mouth",
    "traitValue": "Rainbow Snarl",
    "frequency": 534,
    "pct": 4.806048060480605,
    "desc": "534 of 11111 (4.81%)",
    "example": "https://www.arweave.net/PHd-qZbzFVK15fd6nd1UToHNt-flZuAm4AbaVYnnfjw?ext=png"
  },
  {
    "traitName": "Eyes",
    "traitValue": "Blue Sunnies",
    "frequency": 535,
    "pct": 4.815048150481505,
    "desc": "535 of 11111 (4.82%)",
    "example": "https://www.arweave.net/LdVXOSIxuc_A1oXVqaaQEjTVzEXV8WCYGDq1ETJtpy4?ext=png"
  },
  {
    "traitName": "Mouth",
    "traitValue": "Blunt",
    "frequency": 539,
    "pct": 4.851048510485105,
    "desc": "539 of 11111 (4.85%)",
    "example": "https://www.arweave.net/KYPiTtoz18U1gOSSeOAnz4WrPqykkimLFO8_g93nuyo?ext=png"
  },
  {
    "traitName": "Body",
    "traitValue": "Leopard",
    "frequency": 539,
    "pct": 4.851048510485105,
    "desc": "539 of 11111 (4.85%)",
    "example": "https://www.arweave.net/vgNSt32VmmzK_AXRN8GhYAzHzRa4YULZngq2PkxGG3k?ext=png"
  },
  {
    "traitName": "Mouth",
    "traitValue": "Pearly Whites",
    "frequency": 542,
    "pct": 4.878048780487805,
    "desc": "542 of 11111 (4.88%)",
    "example": "https://www.arweave.net/Tb6pGoW_6pFxmMIRAoPWrXriwjwNjpTTwwRp2nkQxGw?ext=png"
  },
  {
    "traitName": "Eyes",
    "traitValue": "Blue Uzi Shades",
    "frequency": 543,
    "pct": 4.887048870488705,
    "desc": "543 of 11111 (4.89%)",
    "example": "https://www.arweave.net/S6FoXphsmQq8GF5n1ULu25hnnTohG9iLfZwaHbv4c-0?ext=png"
  },
  {
    "traitName": "Mouth",
    "traitValue": "Blue Party Horn",
    "frequency": 548,
    "pct": 4.932049320493205,
    "desc": "548 of 11111 (4.93%)",
    "example": "https://www.arweave.net/oJUMCAtQLD9nTExz_PZQ9cltvvrvOspS-FOY6zUFPro?ext=png"
  },
  {
    "traitName": "Mouth",
    "traitValue": "Party Horn",
    "frequency": 549,
    "pct": 4.941049410494105,
    "desc": "549 of 11111 (4.94%)",
    "example": "https://www.arweave.net/Lyjtp5BkVPGoUJAPwR6-yPKiSmsYDSZ_duVYQAb9j4Q?ext=png"
  },
  {
    "traitName": "Eyes",
    "traitValue": "Green",
    "frequency": 550,
    "pct": 4.950049500495005,
    "desc": "550 of 11111 (4.95%)",
    "example": "https://www.arweave.net/7NfkznOS_Nd4Zab-ynCrmS3FljDMF2S8C8ATyM_bVU4?ext=png"
  },
  {
    "traitName": "Eyes",
    "traitValue": "Reading Glasses",
    "frequency": 556,
    "pct": 5.004050040500405,
    "desc": "556 of 11111 (5.00%)",
    "example": "https://www.arweave.net/OLoTIU4e_WG4eqxIQIDUKYgMYr2adeXWl7rpzDEwRtE?ext=png"
  },
  {
    "traitName": "Mouth",
    "traitValue": "Platinum Grill",
    "frequency": 559,
    "pct": 5.0310503105031055,
    "desc": "559 of 11111 (5.03%)",
    "example": "https://www.arweave.net/OLoTIU4e_WG4eqxIQIDUKYgMYr2adeXWl7rpzDEwRtE?ext=png"
  },
  {
    "traitName": "Mouth",
    "traitValue": "Goblin Tongue",
    "frequency": 561,
    "pct": 5.0490504905049045,
    "desc": "561 of 11111 (5.05%)",
    "example": "https://www.arweave.net/NFeIZWruLJlYVIzo4MFSRV1lzo691NCPZ_45T0_vbVw?ext=png"
  },
  {
    "traitName": "Hair",
    "traitValue": "OG",
    "frequency": 563,
    "pct": 5.067050670506705,
    "desc": "563 of 11111 (5.07%)",
    "example": "https://www.arweave.net/ZUKw-br1gv1hmNuhrb9E3TYNYru2XkOcMsFYP353Bf4?ext=png"
  },
  {
    "traitName": "Body",
    "traitValue": "Shadow",
    "frequency": 566,
    "pct": 5.094050940509405,
    "desc": "566 of 11111 (5.09%)",
    "example": "https://www.arweave.net/HfjqNWyncBZWLzOe1EJM7IUtQqYBY39_OjJg9MdWcA4?ext=png"
  },
  {
    "traitName": "Mouth",
    "traitValue": "Demon",
    "frequency": 567,
    "pct": 5.103051030510305,
    "desc": "567 of 11111 (5.10%)",
    "example": "https://www.arweave.net/P11xsQ1Y-TfJj4QvyMKbB9m2HETo5f_K3W9A0MeQtj0?ext=png"
  },
  {
    "traitName": "Mouth",
    "traitValue": "J Bird",
    "frequency": 569,
    "pct": 5.121051210512105,
    "desc": "569 of 11111 (5.12%)",
    "example": "https://www.arweave.net/7NfkznOS_Nd4Zab-ynCrmS3FljDMF2S8C8ATyM_bVU4?ext=png"
  },
  {
    "traitName": "Eyes",
    "traitValue": "Pink Sunnies",
    "frequency": 569,
    "pct": 5.121051210512105,
    "desc": "569 of 11111 (5.12%)",
    "example": "https://www.arweave.net/KYPiTtoz18U1gOSSeOAnz4WrPqykkimLFO8_g93nuyo?ext=png"
  },
  {
    "traitName": "Mouth",
    "traitValue": "Classic Sewn",
    "frequency": 571,
    "pct": 5.139051390513905,
    "desc": "571 of 11111 (5.14%)",
    "example": "https://www.arweave.net/PuKz7zf8k8HwMVSU0mrV9ykH5W1UcsODkkriTLzDd2U?ext=png"
  },
  {
    "traitName": "Mouth",
    "traitValue": "Snarl",
    "frequency": 572,
    "pct": 5.148051480514805,
    "desc": "572 of 11111 (5.15%)",
    "example": "https://www.arweave.net/TW2ccD8filIyp0wEo1mG-ruxdX62fgQU8euZjEycSwM?ext=png"
  },
  {
    "traitName": "Eyes",
    "traitValue": "Blood Shot",
    "frequency": 573,
    "pct": 5.157051570515705,
    "desc": "573 of 11111 (5.16%)",
    "example": "https://www.arweave.net/HfjqNWyncBZWLzOe1EJM7IUtQqYBY39_OjJg9MdWcA4?ext=png"
  },
  {
    "traitName": "Eyes",
    "traitValue": "Gold Uzi Shades",
    "frequency": 574,
    "pct": 5.166051660516605,
    "desc": "574 of 11111 (5.17%)",
    "example": "https://www.arweave.net/8EeYsuw3scfgpGgA-5tN-NkioWTRg47VSGGe1flwlKo?ext=png"
  },
  {
    "traitName": "Mouth",
    "traitValue": "Mary Jane Pipe",
    "frequency": 582,
    "pct": 5.238052380523806,
    "desc": "582 of 11111 (5.24%)",
    "example": "https://www.arweave.net/mLFOBDuQsbVB2xfDuuWG7_VfElZNVWEf1dqC1VjYQL8?ext=png"
  },
  {
    "traitName": "Mouth",
    "traitValue": "Icey Snarl",
    "frequency": 584,
    "pct": 5.256052560525605,
    "desc": "584 of 11111 (5.26%)",
    "example": "https://www.arweave.net/nYXdmG55nBjSEVK5lR8wO6rhBsrv32yhb5OwyTeNPgs?ext=png"
  },
  {
    "traitName": "Mouth",
    "traitValue": "Kazoo",
    "frequency": 585,
    "pct": 5.265052650526505,
    "desc": "585 of 11111 (5.27%)",
    "example": "https://www.arweave.net/Ar9AQvdmkhgBn9zdGVPgOmKkidJH1vvuS-V1SJ13mdg?ext=png"
  },
  {
    "traitName": "Eyes",
    "traitValue": "Baby Blue",
    "frequency": 585,
    "pct": 5.265052650526505,
    "desc": "585 of 11111 (5.27%)",
    "example": "https://www.arweave.net/ZUKw-br1gv1hmNuhrb9E3TYNYru2XkOcMsFYP353Bf4?ext=png"
  },
  {
    "traitName": "Eyes",
    "traitValue": "3D Pupils",
    "frequency": 590,
    "pct": 5.310053100531005,
    "desc": "590 of 11111 (5.31%)",
    "example": "https://www.arweave.net/NVR_BhDcClJ4fQj7Gj6LvMsF0jUOke0dHyGO843KQF8?ext=png"
  },
  {
    "traitName": "Eyes",
    "traitValue": "Angel Eyes",
    "frequency": 611,
    "pct": 5.499054990549905,
    "desc": "611 of 11111 (5.50%)",
    "example": "https://www.arweave.net/pioLWnQ14zEyTBwpP9PO69OpIeo3fabzbYpd6E62fqM?ext=png"
  },
  {
    "traitName": "Background",
    "traitValue": "Fushcia",
    "frequency": 631,
    "pct": 5.679056790567906,
    "desc": "631 of 11111 (5.68%)",
    "example": "https://www.arweave.net/f-yXFaqmvr5ur3Ac8h1Nc4rfElsFiIHXpiAWW2Lziu0?ext=png"
  },
  {
    "traitName": "Eyes",
    "traitValue": "Red Sunnies",
    "frequency": 637,
    "pct": 5.733057330573306,
    "desc": "637 of 11111 (5.73%)",
    "example": "https://www.arweave.net/9lIuhHKKAMT72Uz_29pFVqMA-F1ICqRWkKkSc_f9pis?ext=png"
  },
  {
    "traitName": "Background",
    "traitValue": "Grey",
    "frequency": 645,
    "pct": 5.805058050580506,
    "desc": "645 of 11111 (5.81%)",
    "example": "https://www.arweave.net/oJUMCAtQLD9nTExz_PZQ9cltvvrvOspS-FOY6zUFPro?ext=png"
  },
  {
    "traitName": "Background",
    "traitValue": "Mint Green",
    "frequency": 649,
    "pct": 5.841058410584106,
    "desc": "649 of 11111 (5.84%)",
    "example": "https://www.arweave.net/MGfnQAsQoOlkTlILBiq-q2GsXhhh52mD9TAd2p-mhyc?ext=png"
  },
  {
    "traitName": "Eyes",
    "traitValue": "Red Uzi Shades",
    "frequency": 651,
    "pct": 5.8590585905859065,
    "desc": "651 of 11111 (5.86%)",
    "example": "https://www.arweave.net/oJUMCAtQLD9nTExz_PZQ9cltvvrvOspS-FOY6zUFPro?ext=png"
  },
  {
    "traitName": "Background",
    "traitValue": "Honey",
    "frequency": 655,
    "pct": 5.895058950589506,
    "desc": "655 of 11111 (5.90%)",
    "example": "https://www.arweave.net/LdVXOSIxuc_A1oXVqaaQEjTVzEXV8WCYGDq1ETJtpy4?ext=png"
  },
  {
    "traitName": "Background",
    "traitValue": "Bubblegum",
    "frequency": 662,
    "pct": 5.958059580595806,
    "desc": "662 of 11111 (5.96%)",
    "example": "https://www.arweave.net/Ar9AQvdmkhgBn9zdGVPgOmKkidJH1vvuS-V1SJ13mdg?ext=png"
  },
  {
    "traitName": "Background",
    "traitValue": "Turquoise",
    "frequency": 663,
    "pct": 5.967059670596706,
    "desc": "663 of 11111 (5.97%)",
    "example": "https://www.arweave.net/9lIuhHKKAMT72Uz_29pFVqMA-F1ICqRWkKkSc_f9pis?ext=png"
  },
  {
    "traitName": "Background",
    "traitValue": "Bumblebee",
    "frequency": 667,
    "pct": 6.003060030600306,
    "desc": "667 of 11111 (6.00%)",
    "example": "https://www.arweave.net/8EeYsuw3scfgpGgA-5tN-NkioWTRg47VSGGe1flwlKo?ext=png"
  },
  {
    "traitName": "Eyes",
    "traitValue": "Yellow Sunnies",
    "frequency": 674,
    "pct": 6.066060660606606,
    "desc": "674 of 11111 (6.07%)",
    "example": "https://www.arweave.net/06vLgNoZ7dfx9xkPtcmp2vy7RrVQq0wkHP3YndkCtJE?ext=png"
  },
  {
    "traitName": "Eyes",
    "traitValue": "White Sunnies",
    "frequency": 675,
    "pct": 6.0750607506075065,
    "desc": "675 of 11111 (6.08%)",
    "example": "https://www.arweave.net/MGfnQAsQoOlkTlILBiq-q2GsXhhh52mD9TAd2p-mhyc?ext=png"
  },
  {
    "traitName": "Eyes",
    "traitValue": "Sleepy",
    "frequency": 679,
    "pct": 6.111061110611106,
    "desc": "679 of 11111 (6.11%)",
    "example": "https://www.arweave.net/PuKz7zf8k8HwMVSU0mrV9ykH5W1UcsODkkriTLzDd2U?ext=png"
  },
  {
    "traitName": "Background",
    "traitValue": "Lavender",
    "frequency": 680,
    "pct": 6.120061200612007,
    "desc": "680 of 11111 (6.12%)",
    "example": "https://www.arweave.net/7NfkznOS_Nd4Zab-ynCrmS3FljDMF2S8C8ATyM_bVU4?ext=png"
  },
  {
    "traitName": "Background",
    "traitValue": "Cerulean",
    "frequency": 682,
    "pct": 6.138061380613806,
    "desc": "682 of 11111 (6.14%)",
    "example": "https://www.arweave.net/Lyjtp5BkVPGoUJAPwR6-yPKiSmsYDSZ_duVYQAb9j4Q?ext=png"
  },
  {
    "traitName": "Background",
    "traitValue": "Matte Red",
    "frequency": 691,
    "pct": 6.219062190621906,
    "desc": "691 of 11111 (6.22%)",
    "example": "https://www.arweave.net/6ham-hnY58MH-p_vPSsFcV2byDehXcRxFMwVUsOJ_XU?ext=png"
  },
  {
    "traitName": "Background",
    "traitValue": "Sky",
    "frequency": 700,
    "pct": 6.300063000630006,
    "desc": "700 of 11111 (6.30%)",
    "example": "https://www.arweave.net/NFeIZWruLJlYVIzo4MFSRV1lzo691NCPZ_45T0_vbVw?ext=png"
  },
  {
    "traitName": "Body",
    "traitValue": "Gold",
    "frequency": 702,
    "pct": 6.318063180631807,
    "desc": "702 of 11111 (6.32%)",
    "example": "https://www.arweave.net/OusoDUMuzsgGE8_ufDXc7ns9p1x7G080rh_qNqM-6Bc?ext=png"
  },
  {
    "traitName": "Background",
    "traitValue": "Orchid",
    "frequency": 730,
    "pct": 6.570065700657006,
    "desc": "730 of 11111 (6.57%)",
    "example": "https://www.arweave.net/Hm52aXpfvE7tinV_q9U6SBSJxxz0S0SIYqQ1jLPmcgI?ext=png"
  },
  {
    "traitName": "Background",
    "traitValue": "Brown",
    "frequency": 737,
    "pct": 6.633066330663306,
    "desc": "737 of 11111 (6.63%)",
    "example": "https://www.arweave.net/Z2aPirpabGCl1FT2MMwPpMmwEVxHwJmNWYuxjuajaBw?ext=png"
  },
  {
    "traitName": "Background",
    "traitValue": "Alien Green",
    "frequency": 742,
    "pct": 6.678066780667807,
    "desc": "742 of 11111 (6.68%)",
    "example": "https://www.arweave.net/OLoTIU4e_WG4eqxIQIDUKYgMYr2adeXWl7rpzDEwRtE?ext=png"
  },
  {
    "traitName": "Background",
    "traitValue": "Army Green",
    "frequency": 786,
    "pct": 7.074070740707407,
    "desc": "786 of 11111 (7.07%)",
    "example": "https://www.arweave.net/KYPiTtoz18U1gOSSeOAnz4WrPqykkimLFO8_g93nuyo?ext=png"
  },
  {
    "traitName": "Background",
    "traitValue": "Blood Red",
    "frequency": 790,
    "pct": 7.110071100711007,
    "desc": "790 of 11111 (7.11%)",
    "example": "https://www.arweave.net/HfjqNWyncBZWLzOe1EJM7IUtQqYBY39_OjJg9MdWcA4?ext=png"
  },
  {
    "traitName": "Jewelry",
    "traitValue": "Gold Hoop",
    "frequency": 860,
    "pct": 7.740077400774008,
    "desc": "860 of 11111 (7.74%)",
    "example": "https://www.arweave.net/8y0ClrYjzENRhKLwLtYKGBKgVbK3T_aEl_1hgs-AiYs?ext=png"
  },
  {
    "traitName": "Jewelry",
    "traitValue": "Red Nose Ring",
    "frequency": 869,
    "pct": 7.821078210782108,
    "desc": "869 of 11111 (7.82%)",
    "example": "https://www.arweave.net/NVR_BhDcClJ4fQj7Gj6LvMsF0jUOke0dHyGO843KQF8?ext=png"
  },
  {
    "traitName": "Jewelry",
    "traitValue": "Dangly Gold Diamonds",
    "frequency": 870,
    "pct": 7.830078300783009,
    "desc": "870 of 11111 (7.83%)",
    "example": "https://www.arweave.net/NFeIZWruLJlYVIzo4MFSRV1lzo691NCPZ_45T0_vbVw?ext=png"
  },
  {
    "traitName": "Jewelry",
    "traitValue": "Dangly Blue Diamonds",
    "frequency": 872,
    "pct": 7.848078480784808,
    "desc": "872 of 11111 (7.85%)",
    "example": "https://www.arweave.net/7NfkznOS_Nd4Zab-ynCrmS3FljDMF2S8C8ATyM_bVU4?ext=png"
  },
  {
    "traitName": "Jewelry",
    "traitValue": "Blooded Bling",
    "frequency": 882,
    "pct": 7.938079380793808,
    "desc": "882 of 11111 (7.94%)",
    "example": "https://www.arweave.net/nYXdmG55nBjSEVK5lR8wO6rhBsrv32yhb5OwyTeNPgs?ext=png"
  },
  {
    "traitName": "Jewelry",
    "traitValue": "Multi Color Dangly Diamond",
    "frequency": 882,
    "pct": 7.938079380793808,
    "desc": "882 of 11111 (7.94%)",
    "example": "https://www.arweave.net/srdE7L9kv7-fzynBaYLGzK2ttxFWHdQ8JrCZH11qLBw?ext=png"
  },
  {
    "traitName": "Jewelry",
    "traitValue": "Cross Earring",
    "frequency": 898,
    "pct": 8.082080820808208,
    "desc": "898 of 11111 (8.08%)",
    "example": "https://www.arweave.net/MGfnQAsQoOlkTlILBiq-q2GsXhhh52mD9TAd2p-mhyc?ext=png"
  },
  {
    "traitName": "Jewelry",
    "traitValue": "Gold Nose Ring",
    "frequency": 903,
    "pct": 8.127081270812708,
    "desc": "903 of 11111 (8.13%)",
    "example": "https://www.arweave.net/oJUMCAtQLD9nTExz_PZQ9cltvvrvOspS-FOY6zUFPro?ext=png"
  },
  {
    "traitName": "Jewelry",
    "traitValue": "Gold Hoop and Diamond",
    "frequency": 911,
    "pct": 8.199081990819908,
    "desc": "911 of 11111 (8.20%)",
    "example": "https://www.arweave.net/pioLWnQ14zEyTBwpP9PO69OpIeo3fabzbYpd6E62fqM?ext=png"
  },
  {
    "traitName": "Jewelry",
    "traitValue": "Blue Nose Ring",
    "frequency": 926,
    "pct": 8.334083340833407,
    "desc": "926 of 11111 (8.33%)",
    "example": "https://www.arweave.net/Ar9AQvdmkhgBn9zdGVPgOmKkidJH1vvuS-V1SJ13mdg?ext=png"
  },
  {
    "traitName": "Jewelry",
    "traitValue": "Silver Nose Ring",
    "frequency": 955,
    "pct": 8.59508595085951,
    "desc": "955 of 11111 (8.60%)",
    "example": "https://www.arweave.net/9lIuhHKKAMT72Uz_29pFVqMA-F1ICqRWkKkSc_f9pis?ext=png"
  },
  {
    "traitName": "Hair",
    "traitValue": "Ice",
    "frequency": 1067,
    "pct": 9.603096030960309,
    "desc": "1067 of 11111 (9.60%)",
    "example": "https://www.arweave.net/mLFOBDuQsbVB2xfDuuWG7_VfElZNVWEf1dqC1VjYQL8?ext=png"
  },
  {
    "traitName": "Hair",
    "traitValue": "Green",
    "frequency": 1080,
    "pct": 9.72009720097201,
    "desc": "1080 of 11111 (9.72%)",
    "example": "https://www.arweave.net/8HZvKpj5j4kr0Ph06QiulezX_X3kFFc-Uvqy6rnnku4?ext=png"
  },
  {
    "traitName": "Hair",
    "traitValue": "Turquoise",
    "frequency": 1081,
    "pct": 9.72909729097291,
    "desc": "1081 of 11111 (9.73%)",
    "example": "https://www.arweave.net/pioLWnQ14zEyTBwpP9PO69OpIeo3fabzbYpd6E62fqM?ext=png"
  },
  {
    "traitName": "Hair",
    "traitValue": "Blonde",
    "frequency": 1113,
    "pct": 10.01710017100171,
    "desc": "1113 of 11111 (10.02%)",
    "example": "https://www.arweave.net/oJUMCAtQLD9nTExz_PZQ9cltvvrvOspS-FOY6zUFPro?ext=png"
  },
  {
    "traitName": "Hair",
    "traitValue": "Azure",
    "frequency": 1113,
    "pct": 10.01710017100171,
    "desc": "1113 of 11111 (10.02%)",
    "example": "https://www.arweave.net/nYXdmG55nBjSEVK5lR8wO6rhBsrv32yhb5OwyTeNPgs?ext=png"
  },
  {
    "traitName": "Hair",
    "traitValue": "Red",
    "frequency": 1121,
    "pct": 10.089100891008911,
    "desc": "1121 of 11111 (10.09%)",
    "example": "https://www.arweave.net/MGfnQAsQoOlkTlILBiq-q2GsXhhh52mD9TAd2p-mhyc?ext=png"
  },
  {
    "traitName": "Hair",
    "traitValue": "Purple",
    "frequency": 1122,
    "pct": 10.098100981009809,
    "desc": "1122 of 11111 (10.10%)",
    "example": "https://www.arweave.net/9lIuhHKKAMT72Uz_29pFVqMA-F1ICqRWkKkSc_f9pis?ext=png"
  },
  {
    "traitName": "Hair",
    "traitValue": "Cobalt",
    "frequency": 1144,
    "pct": 10.29610296102961,
    "desc": "1144 of 11111 (10.30%)",
    "example": "https://www.arweave.net/Ar9AQvdmkhgBn9zdGVPgOmKkidJH1vvuS-V1SJ13mdg?ext=png"
  },
  {
    "traitName": "Hair",
    "traitValue": "Magenta",
    "frequency": 1158,
    "pct": 10.422104221042211,
    "desc": "1158 of 11111 (10.42%)",
    "example": "https://www.arweave.net/NFeIZWruLJlYVIzo4MFSRV1lzo691NCPZ_45T0_vbVw?ext=png"
  },
  {
    "traitName": "Body",
    "traitValue": "Devil",
    "frequency": 1169,
    "pct": 10.521105211052111,
    "desc": "1169 of 11111 (10.52%)",
    "example": "https://www.arweave.net/9lIuhHKKAMT72Uz_29pFVqMA-F1ICqRWkKkSc_f9pis?ext=png"
  },
  {
    "traitName": "Body",
    "traitValue": "Blue",
    "frequency": 1206,
    "pct": 10.854108541085411,
    "desc": "1206 of 11111 (10.85%)",
    "example": "https://www.arweave.net/7NfkznOS_Nd4Zab-ynCrmS3FljDMF2S8C8ATyM_bVU4?ext=png"
  },
  {
    "traitName": "Body",
    "traitValue": "Alien",
    "frequency": 1214,
    "pct": 10.926109261092611,
    "desc": "1214 of 11111 (10.93%)",
    "example": "https://www.arweave.net/8y0ClrYjzENRhKLwLtYKGBKgVbK3T_aEl_1hgs-AiYs?ext=png"
  },
  {
    "traitName": "Body",
    "traitValue": "Tan",
    "frequency": 1222,
    "pct": 10.99810998109981,
    "desc": "1222 of 11111 (11.00%)",
    "example": "https://www.arweave.net/S6FoXphsmQq8GF5n1ULu25hnnTohG9iLfZwaHbv4c-0?ext=png"
  },
  {
    "traitName": "Body",
    "traitValue": "Violet",
    "frequency": 1223,
    "pct": 11.00711007110071,
    "desc": "1223 of 11111 (11.01%)",
    "example": "https://www.arweave.net/NFeIZWruLJlYVIzo4MFSRV1lzo691NCPZ_45T0_vbVw?ext=png"
  },
  {
    "traitName": "Body",
    "traitValue": "Honey",
    "frequency": 1240,
    "pct": 11.16011160111601,
    "desc": "1240 of 11111 (11.16%)",
    "example": "https://www.arweave.net/Ar9AQvdmkhgBn9zdGVPgOmKkidJH1vvuS-V1SJ13mdg?ext=png"
  },
  {
    "traitName": "Body",
    "traitValue": "Uzi",
    "frequency": 1287,
    "pct": 11.583115831158311,
    "desc": "1287 of 11111 (11.58%)",
    "example": "https://www.arweave.net/pioLWnQ14zEyTBwpP9PO69OpIeo3fabzbYpd6E62fqM?ext=png"
  },
  {
    "traitName": "Attributes Count",
    "traitValue": "8",
    "frequency": 11109,
    "pct": 99.98199981999821,
    "desc": "11109 of 11111 (99.98%)",
    "example": "https://www.arweave.net/9lIuhHKKAMT72Uz_29pFVqMA-F1ICqRWkKkSc_f9pis?ext=png"
  }
]